basingse/.gitignore
basingse/__init__.py
basingse/_version.py
basingse/app.py
basingse/assets.py
basingse/autoimport.py
basingse/htmx.py
basingse/logging.py
basingse/markdown.py
basingse/py.typed
basingse/settings.py
basingse/svcs.py
basingse/views.py
basingse/admin/__init__.py
basingse/admin/extension.py
basingse/admin/forms.py
basingse/admin/portal.py
basingse/admin/settings.py
basingse/admin/views.py
basingse/admin/templates/admin/_breadcrumbs.html
basingse/admin/templates/admin/_link_form_field.html
basingse/admin/templates/admin/_modal.html
basingse/admin/templates/admin/_sidebar.html
basingse/admin/templates/admin/bad_request.html
basingse/admin/templates/admin/base.html
basingse/admin/templates/admin/home.html
basingse/admin/templates/admin/not_found.html
basingse/admin/templates/admin/attachment/_field.html
basingse/admin/templates/admin/base/_controls.html
basingse/admin/templates/admin/base/edit.html
basingse/admin/templates/admin/base/list.html
basingse/admin/templates/admin/portal/_form.html
basingse/admin/templates/admin/portal/edit.html
basingse/admin/templates/admin/portal/list.html
basingse/admin/templates/admin/portal/preview.html
basingse/admin/templates/admin/sidebar/user.html
basingse/assets/manifest.json
basingse/assets/css/basingse.admin.d381eb5ee21b72af0f39.css
basingse/assets/css/basingse.admin.d381eb5ee21b72af0f39.css.map
basingse/assets/css/basingse.bootstrap.e9a17d291f5bd5588778.css
basingse/assets/css/basingse.bootstrap.e9a17d291f5bd5588778.css.map
basingse/assets/css/basingse.main.f4a07c39ee362875fc7b.css
basingse/assets/css/basingse.main.f4a07c39ee362875fc7b.css.map
basingse/assets/js/basingse.admin.bc91f6d052798f954982.js
basingse/assets/js/basingse.admin.bc91f6d052798f954982.js.map
basingse/assets/js/basingse.bootstrap.0309905388accc85e483.js
basingse/assets/js/basingse.bootstrap.0309905388accc85e483.js.map
basingse/assets/js/basingse.debug.c915b164a8bac01dc018.js
basingse/assets/js/basingse.debug.c915b164a8bac01dc018.js.map
basingse-0.6.0.dist-info/METADATA
basingse-0.6.0.dist-info/WHEEL
basingse-0.6.0.dist-info/licenses/LICENSE
basingse-0.6.0.dist-info/RECORD
